{
  "id": 145,
  "name": "썬더",
  "stats": {
    "H": 90,
    "A": 90,
    "B": 85,
    "C": 125,
    "D": 90,
    "S": 100
  },
  "abilities": [
    "프레셔",
    "정전기"
  ],
  "moves": [
    "칼바람",
    "날려버리기",
    "공중날기",
    "박치기",
    "돌진",
    "이판사판태클",
    "째려보기",
    "울부짖기",
    "파괴광선",
    "쪼기",
    "회전부리",
    "전기쇼크",
    "10만볼트",
    "전기자석파",
    "번개",
    "맹독",
    "고속이동",
    "분노",
    "흉내내기",
    "그림자분신",
    "빛의장막",
    "리플렉터",
    "참기",
    "스피드스타",
    "불새",
    "플래시",
    "잠자기",
    "대타출동",
    "코골기",
    "저주",
    "방어",
    "진흙뿌리기",
    "전자포",
    "판별",
    "모래바람",
    "버티기",
    "뽐내기",
    "강철날개",
    "잠꼬대",
    "은혜갚기",
    "화풀이",
    "바톤터치",
    "잠재파워",
    "회오리",
    "비바라기",
    "쾌청",
    "원시의힘",
    "바위깨기",
    "열풍",
    "싸라기눈",
    "객기",
    "충전",
    "도우미",
    "비밀의힘",
    "웨더볼",
    "에어컷터",
    "금속음",
    "시그널빔",
    "신통력",
    "제비반환",
    "전격파",
    "날개쉬기",
    "자연의은혜",
    "쪼아대기",
    "순풍",
    "유턴",
    "브레이브버드",
    "기가임팩트",
    "안개제거",
    "방전",
    "차지빔",
    "괴상한바람",
    "일렉트릭볼",
    "돌림노래",
    "프리폴",
    "애크러뱃",
    "볼트체인지",
    "와일드볼트",
    "폭풍",
    "비밀이야기",
    "괴전파",
    "자기장조작",
    "일렉트릭필드",
    "예민해지기",
    "라이징볼트",
    "더블윙",
    "테라버스트",
    "썬더다이브"
  ]
}