{
  "id": 207,
  "name": "글라이거",
  "stats": {
    "H": 65,
    "A": 75,
    "B": 105,
    "C": 35,
    "D": 65,
    "S": 85
  },
  "abilities": [
    "괴력집게",
    "모래숨기",
    "면역"
  ],
  "moves": [
    "가위자르기",
    "칼바람",
    "칼춤",
    "풀베기",
    "날개치기",
    "모래뿌리기",
    "박치기",
    "돌진",
    "이판사판태클",
    "독침",
    "카운터",
    "괴력",
    "지진",
    "구멍파기",
    "맹독",
    "고속이동",
    "전광석화",
    "흉내내기",
    "싫은소리",
    "그림자분신",
    "단단해지기",
    "스피드스타",
    "꿈먹기",
    "찝게햄머",
    "잠자기",
    "스톤샤워",
    "베어가르기",
    "대타출동",
    "도둑질",
    "코골기",
    "저주",
    "방어",
    "겁나는얼굴",
    "속여때리기",
    "오물폭탄",
    "진흙뿌리기",
    "압정뿌리기",
    "판별",
    "모래바람",
    "버티기",
    "칼등치기",
    "뽐내기",
    "연속자르기",
    "강철날개",
    "헤롱헤롱",
    "잠꼬대",
    "은혜갚기",
    "화풀이",
    "바톤터치",
    "아이언테일",
    "메탈크로우",
    "잠재파워",
    "비바라기",
    "쾌청",
    "깨물어부수기",
    "바위깨기",
    "트집",
    "객기",
    "도발",
    "깨트리다",
    "탁쳐서떨구기",
    "비밀의힘",
    "암석봉인",
    "스카이업퍼",
    "모래지옥",
    "제비반환",
    "머드숏",
    "포이즌테일",
    "날개쉬기",
    "자연의은혜",
    "페인트",
    "순풍",
    "유턴",
    "보복",
    "내던지기",
    "파워트릭",
    "독압정",
    "록커트",
    "독찌르기",
    "악의파동",
    "깜짝베기",
    "아쿠아테일",
    "시저크로스",
    "대지의힘",
    "번개엄니",
    "얼음엄니",
    "불꽃엄니",
    "진흙폭탄",
    "락클라임",
    "안개제거",
    "크로스포이즌",
    "더스트슈트",
    "스톤에지",
    "유혹",
    "스텔스록",
    "벌레먹음",
    "손톱갈기",
    "베놈쇼크",
    "돌림노래",
    "애크러뱃",
    "벌레의저항",
    "땅고르기",
    "비밀이야기",
    "10만마력",
    "지옥찌르기",
    "덤벼들기",
    "사이코팽",
    "와이드브레이커",
    "스케일샷",
    "엄습하는일격",
    "더블윙",
    "테라버스트"
  ]
}