{
  "id": 375,
  "name": "메탕구",
  "stats": {
    "H": 60,
    "A": 75,
    "B": 100,
    "C": 55,
    "D": 80,
    "S": 50
  },
  "abilities": [
    "클리어바디",
    "라이트메탈"
  ],
  "moves": [
    "냉동펀치",
    "번개펀치",
    "풀베기",
    "박치기",
    "몸통박치기",
    "누르기",
    "돌진",
    "이판사판태클",
    "파괴광선",
    "괴력",
    "지진",
    "맹독",
    "염동력",
    "사이코키네시스",
    "고속이동",
    "흉내내기",
    "그림자분신",
    "웅크리기",
    "빛의장막",
    "리플렉터",
    "자폭",
    "스피드스타",
    "플래시",
    "대폭발",
    "잠자기",
    "스톤샤워",
    "대타출동",
    "코골기",
    "방어",
    "겁나는얼굴",
    "오물폭탄",
    "진흙뿌리기",
    "얼다바람",
    "모래바람",
    "버티기",
    "구르기",
    "뽐내기",
    "연속자르기",
    "잠꼬대",
    "은혜갚기",
    "화풀이",
    "폭발펀치",
    "따라가때리기",
    "메탈크로우",
    "잠재파워",
    "비바라기",
    "쾌청",
    "자기암시",
    "섀도볼",
    "미래예지",
    "바위깨기",
    "객기",
    "힘껏펀치",
    "트릭",
    "깨트리다",
    "비밀의힘",
    "코멧펀치",
    "암석봉인",
    "코스믹파워",
    "시그널빔",
    "제비반환",
    "철벽",
    "중력",
    "미라클아이",
    "자이로볼",
    "자연의은혜",
    "전자부유",
    "록커트",
    "기가임팩트",
    "불릿펀치",
    "사이코커터",
    "사념의박치기",
    "러스터캐논",
    "아이언헤드",
    "스텔스록",
    "풀묶기",
    "손톱갈기",
    "사이코쇼크",
    "텔레키네시스",
    "헤비봄버",
    "돌림노래",
    "사이드체인지",
    "땅고르기",
    "비밀이야기",
    "그로우펀치",
    "철제광선",
    "와이드포스",
    "아이언롤러",
    "메테오빔",
    "테라버스트",
    "개척하기",
    "하드프레스",
    "사이코노이즈"
  ]
}