{
  "id": 427,
  "name": "이어롤",
  "stats": {
    "H": 55,
    "A": 66,
    "B": 44,
    "C": 44,
    "D": 56,
    "S": 85
  },
  "abilities": [
    "도주",
    "서투름",
    "유연"
  ],
  "moves": [
    "막치기",
    "메가톤펀치",
    "불꽃펀치",
    "냉동펀치",
    "번개펀치",
    "풀베기",
    "두번치기",
    "메가톤킥",
    "점프킥",
    "박치기",
    "이판사판태클",
    "냉동빔",
    "안다리걸기",
    "솔라빔",
    "10만볼트",
    "전기자석파",
    "구멍파기",
    "맹독",
    "고속이동",
    "전광석화",
    "그림자분신",
    "웅크리기",
    "스피드스타",
    "잼잼펀치",
    "튀어오르기",
    "잠자기",
    "대타출동",
    "코골기",
    "바둥바둥",
    "방어",
    "천사의키스",
    "진흙뿌리기",
    "꿰뚫어보기",
    "버티기",
    "애교부리기",
    "뽐내기",
    "헤롱헤롱",
    "잠꼬대",
    "치료방울",
    "은혜갚기",
    "화풀이",
    "바톤터치",
    "앵콜",
    "아이언테일",
    "잠재파워",
    "비바라기",
    "쾌청",
    "섀도볼",
    "바위깨기",
    "속이다",
    "소란피기",
    "부추기기",
    "객기",
    "힘껏펀치",
    "도우미",
    "매직코트",
    "죽기살기",
    "비밀의힘",
    "흔들흔들댄스",
    "흙놀이",
    "하이퍼보이스",
    "거짓울음",
    "코스믹파워",
    "스카이업퍼",
    "뛰어오르다",
    "탐내다",
    "전격파",
    "물의파동",
    "치유소원",
    "자연의은혜",
    "보복",
    "승부굳히기",
    "내던지기",
    "흉내쟁이",
    "뒀다쓰기",
    "드레인펀치",
    "바꿔치기",
    "유혹",
    "풀묶기",
    "차지빔",
    "더블어택",
    "로킥",
    "동료만들기",
    "당신먼저",
    "돌림노래",
    "배대뒤치기",
    "원수갚기",
    "분발",
    "드레인키스",
    "치근거리기",
    "비밀이야기",
    "초롱초롱눈동자",
    "그로우펀치",
    "트리플악셀"
  ]
}