{
  "id": 568,
  "name": "깨봉이",
  "stats": {
    "H": 50,
    "A": 50,
    "B": 62,
    "C": 40,
    "D": 62,
    "S": 65
  },
  "abilities": [
    "악취",
    "점착",
    "유폭"
  ],
  "moves": [
    "막치기",
    "연속뺨치기",
    "모래뿌리기",
    "돌진",
    "맹독",
    "그림자분신",
    "흑안개",
    "자폭",
    "오물공격",
    "망각술",
    "독가스",
    "대폭발",
    "잠자기",
    "대타출동",
    "도둑질",
    "코골기",
    "저주",
    "원한",
    "방어",
    "오물폭탄",
    "압정뿌리기",
    "기가드레인",
    "버티기",
    "구르기",
    "뽐내기",
    "헤롱헤롱",
    "잠꼬대",
    "은혜갚기",
    "화풀이",
    "아픔나누기",
    "잠재파워",
    "비바라기",
    "쾌청",
    "비축하기",
    "꿀꺽",
    "객기",
    "리사이클",
    "비밀의힘",
    "흙놀이",
    "락블레스트",
    "보복",
    "독압정",
    "악의파동",
    "씨폭탄",
    "드레인펀치",
    "더스트슈트",
    "베놈쇼크",
    "바디퍼지",
    "오물웨이브",
    "애시드봄",
    "돌림노래",
    "클리어스모그",
    "트림",
    "비밀이야기",
    "베놈트랩",
    "엉겨붙기",
    "부식가스"
  ]
}